LICENSE
README.md
setup.cfg
setup.py
versioneer.py
q2_mislabeled/__init__.py
q2_mislabeled/_format.py
q2_mislabeled/_pipelines.py
q2_mislabeled/_transformers.py
q2_mislabeled/_types.py
q2_mislabeled/_version.py
q2_mislabeled/plugin_setup.py
q2_mislabeled.egg-info/PKG-INFO
q2_mislabeled.egg-info/SOURCES.txt
q2_mislabeled.egg-info/dependency_links.txt
q2_mislabeled.egg-info/entry_points.txt
q2_mislabeled.egg-info/not-zip-safe
q2_mislabeled.egg-info/requires.txt
q2_mislabeled.egg-info/top_level.txt
q2_mislabeled/tests/__init__.py
q2_mislabeled/tests/test_pipelines.py
q2_mislabeled/tests/test_transformers.py